azure_waf_deployer/__init__.py
azure_waf_deployer/cli.py
azure_waf_deployer/templates.py
azure_waf_deployer-1.0.0.dist-info/METADATA
azure_waf_deployer-1.0.0.dist-info/WHEEL
azure_waf_deployer-1.0.0.dist-info/entry_points.txt
azure_waf_deployer-1.0.0.dist-info/top_level.txt
azure_waf_deployer-1.0.0.dist-info/RECORD
