Metadata-Version: 2.4
Name: azure-waf-deployer
Version: 1.0.0
Summary: Azure Web Application Firewall deployment templates and utilities
Home-page: https://github.com/yourusername/azure-waf-deployer
Author: Your Name
Author-email: your.email@example.com
Project-URL: Bug Reports, https://github.com/yourusername/azure-waf-deployer/issues
Project-URL: Source, https://github.com/yourusername/azure-waf-deployer
Project-URL: Documentation, https://azure-waf-deployer.readthedocs.io/
Classifier: Development Status :: 4 - Beta
Classifier: Intended Audience :: Developers
Classifier: License :: OSI Approved :: MIT License
Classifier: Operating System :: OS Independent
Classifier: Programming Language :: Python :: 3
Classifier: Programming Language :: Python :: 3.8
Classifier: Programming Language :: Python :: 3.9
Classifier: Programming Language :: Python :: 3.10
Classifier: Programming Language :: Python :: 3.11
Requires-Python: >=3.8
Requires-Dist: azure-identity>=1.12.0
Requires-Dist: azure-mgmt-resource>=22.0.0
Requires-Dist: azure-mgmt-network>=25.0.0
Requires-Dist: azure-mgmt-web>=7.0.0
Requires-Dist: azure-cli-core>=2.45.0
Requires-Dist: jinja2>=3.1.2
Requires-Dist: pyyaml>=6.0
Requires-Dist: click>=8.0.0
Requires-Dist: rich>=13.0.0
Provides-Extra: dev
Requires-Dist: pytest>=7.0.0; extra == "dev"
Requires-Dist: black>=22.0.0; extra == "dev"
Requires-Dist: flake8>=5.0.0; extra == "dev"
Requires-Dist: mypy>=1.0.0; extra == "dev"
Dynamic: author
Dynamic: author-email
Dynamic: classifier
Dynamic: description
Dynamic: description-content-type
Dynamic: home-page
Dynamic: project-url
Dynamic: provides-extra
Dynamic: requires-dist
Dynamic: requires-python
Dynamic: summary
